{
	"BAY": {
		"last_updated": "2019-12-06T09:39:04.000Z",
		"price": 0.00229271883992,
		"floor": 0.2,
		"pegvote": "deflate",
		"volume_24h": 2699.09467509211,
		"percent_change_1h": -0.259419,
		"percent_change_24h": 55.9325,
		"percent_change_7d": -44.4792,
		"market_cap": 2320568.28057858
	},
	"BTC": {
		"last_updated": "2019-12-06T09:39:38.000Z",
		"price": 7402.82259626,
		"floor": 20000,
		"pegvote": "",
		"volume_24h": 17486985368.9836,
		"percent_change_1h": -0.210592,
		"percent_change_24h": 0.646107,
		"percent_change_7d": -2.19145,
		"market_cap": 133888833803.78386
	}
}