{
	"BAY": {
		"last_updated": "2019-08-26T09:11:01.000Z",
		"price": 0.00351526559869,
		"floor": 0.2,
		"pegvote": "deflate",
		"volume_24h": 713.392136204713,
		"percent_change_1h": 0.0113743,
		"percent_change_24h": 2.10672,
		"percent_change_7d": 33.5788,
		"market_cap": 3557965.20013493
	},
	"BTC": {
		"last_updated": "2019-08-26T09:10:27.000Z",
		"price": 10338.6513769,
		"floor": 20000,
		"pegvote": "",
		"volume_24h": 18433528930.9171,
		"percent_change_1h": 0.0209108,
		"percent_change_24h": 2.0337,
		"percent_change_7d": -2.50546,
		"market_cap": 185038463278.44406
	}
}