{
	"BAY": {
		"last_updated": "2019-08-23T09:04:02.000Z",
		"price": 0.00346711198712,
		"floor": 0.2,
		"pegvote": "deflate",
		"volume_24h": 703.619785621879,
		"percent_change_1h": 0.0793929,
		"percent_change_24h": 1.97959,
		"percent_change_7d": 117.738,
		"market_cap": 3509226.671162689
	},
	"BTC": {
		"last_updated": "2019-08-23T09:03:34.000Z",
		"price": 10208.282466,
		"floor": 20000,
		"pegvote": "",
		"volume_24h": 15509962402.8628,
		"percent_change_1h": 0.0472546,
		"percent_change_24h": 2.01425,
		"percent_change_7d": 1.14318,
		"market_cap": 182645436345.75336
	}
}