{
	"BAY": {
		"last_updated": "2020-04-06T21:50:04.000Z",
		"price": 0.14049773541488159,
		"floor": 0.2,
		"floorjump": false,
		"pegvote": "deflate",
		"volume_24h": 46991.1683990328,
		"percent_change_1h": 0.529493,
		"percent_change_24h": 23.339,
		"percent_change_7d": 56.0534,
		"market_cap": 142420432.39853472
	},
	"BTC": {
		"last_updated": "2020-04-06T21:50:46.000Z",
		"price": 7227.24976414,
		"floor": 20000,
		"floorjump": false,
		"pegvote": "",
		"volume_24h": 45759317992.752,
		"percent_change_1h": 0.238317,
		"percent_change_24h": 6.58828,
		"percent_change_7d": 12.4551,
		"market_cap": 132324077294.12746
	}
}