{
	"BAY": {
		"last_updated": "2019-03-08T04:33:01.000Z",
		"price": 0.0065747310575,
		"volume_24h": 74939.6748453852,
		"percent_change_1h": 2.25997,
		"percent_change_24h": -2.0441,
		"percent_change_7d": 7.08782,
		"market_cap": 6654593.698851332
	},
	"BTC": {
		"last_updated": "2019-03-08T04:33:26.000Z",
		"price": 3914.57365566,
		"volume_24h": 9403162123.64542,
		"percent_change_1h": 0.0313125,
		"percent_change_24h": -0.362339,
		"percent_change_7d": 1.39701,
		"market_cap": 68805431612.66438
	}
}