{
	"BAY": {
		"last_updated": "2019-04-25T18:56:00.000Z",
		"price": 0.00990172353248,
		"volume_24h": 132672.574785996,
		"percent_change_1h": 2.54167,
		"percent_change_24h": -0.438214,
		"percent_change_7d": -1.12527,
		"market_cap": 10021998.839305278
	},
	"BTC": {
		"last_updated": "2019-04-25T18:55:30.000Z",
		"price": 5529.21228996,
		"volume_24h": 14252507327.7247,
		"percent_change_1h": 0.0995759,
		"percent_change_24h": 1.35822,
		"percent_change_7d": 4.50146,
		"market_cap": 97674154373.91988
	}
}