{
	"BAY": {
		"last_updated": "2020-03-18T04:11:05.000Z",
		"price": 0.021448926540387003,
		"floor": 0.2,
		"floorjump": false,
		"pegvote": "deflate",
		"volume_24h": 22546.5834617232,
		"percent_change_1h": 0.238112,
		"percent_change_24h": -5.07819,
		"percent_change_7d": 39.617,
		"market_cap": 21688924.517915774
	},
	"BTC": {
		"last_updated": "2020-03-18T04:10:39.000Z",
		"price": 5296.03124454,
		"floor": 20000,
		"floorjump": false,
		"pegvote": "",
		"volume_24h": 36408350884.961,
		"percent_change_1h": 0.852415,
		"percent_change_24h": 3.72616,
		"percent_change_7d": -33.0205,
		"market_cap": 96787619009.59077
	}
}