{
	"BAY": {
		"last_updated": "2019-03-01T13:54:01.000Z",
		"price": 0.00601293104146,
		"volume_24h": 6110.38891123693,
		"percent_change_1h": -0.78265,
		"percent_change_24h": -3.05108,
		"percent_change_7d": -11.6058,
		"market_cap": 6085969.550721398
	},
	"BTC": {
		"last_updated": "2019-03-01T13:54:22.000Z",
		"price": 3870.25242089,
		"volume_24h": 8104022547.44881,
		"percent_change_1h": 0.0825523,
		"percent_change_24h": -0.0384021,
		"percent_change_7d": -2.92824,
		"market_cap": 67981223728.58295
	}
}