{
	"BAY": {
		"last_updated": "2020-01-20T18:06:02.000Z",
		"price": 0.00291166657259,
		"floor": 0.2,
		"pegvote": "inflate",
		"volume_24h": 0,
		"percent_change_1h": 0,
		"percent_change_24h": 7.10543e-14,
		"percent_change_7d": -2.27374e-13,
		"market_cap": 2947034.3132911436
	},
	"BTC": {
		"last_updated": "2020-02-17T05:43:40.000Z",
		"price": 9790.19692052,
		"floor": 20000,
		"pegvote": "",
		"volume_24h": 44306791739.6608,
		"percent_change_1h": 0.103667,
		"percent_change_24h": -1.935,
		"percent_change_7d": -2.12876,
		"market_cap": 178393414444.2333
	}
}