{
	"BAY": {
		"last_updated": "2019-03-13T15:41:02.000Z",
		"price": 0.006819103995,
		"volume_24h": 8332.99794877537,
		"percent_change_1h": 1.40057,
		"percent_change_24h": 0.305387,
		"percent_change_7d": 3.80717,
		"market_cap": 6901935.011497456
	},
	"BTC": {
		"last_updated": "2019-03-13T15:41:28.000Z",
		"price": 3903.69754091,
		"volume_24h": 9342715096.84315,
		"percent_change_1h": -0.300855,
		"percent_change_24h": -0.271329,
		"percent_change_7d": 0.0596056,
		"market_cap": 68651400878.82849
	}
}