{
	"BAY": {
		"last_updated": "2020-03-10T05:18:01.000Z",
		"price": 0.0161748099555432,
		"floor": 0.2,
		"pegvote": "deflate",
		"volume_24h": 2084.11745161135,
		"percent_change_1h": -0.119688,
		"percent_change_24h": 42.3573,
		"percent_change_7d": 71.8665,
		"market_cap": 16353735.511460055
	},
	"BTC": {
		"last_updated": "2020-03-10T05:18:35.000Z",
		"price": 7928.82840958,
		"floor": 20000,
		"pegvote": "",
		"volume_24h": 43979597716.0742,
		"percent_change_1h": -0.0971888,
		"percent_change_24h": 0.100732,
		"percent_change_7d": -10.256,
		"market_cap": 144804391464.86978
	}
}