{
	"BAY": {
		"last_updated": "2020-01-06T12:31:02.000Z",
		"price": 0.00291166657259,
		"floor": 0.2,
		"pegvote": "deflate",
		"volume_24h": 0,
		"percent_change_1h": 0,
		"percent_change_24h": 7.10543e-14,
		"percent_change_7d": -2.27374e-13,
		"market_cap": 2947034.3132911436
	},
	"BTC": {
		"last_updated": "2020-01-06T12:30:35.000Z",
		"price": 7576.20093188,
		"floor": 20000,
		"pegvote": "",
		"volume_24h": 20970513690.5676,
		"percent_change_1h": -0.126544,
		"percent_change_24h": 1.16412,
		"percent_change_7d": 2.82888,
		"market_cap": 137467605153.04764
	}
}