{
	"BAY": {
		"last_updated": "2019-01-15T15:16:07.000Z",
		"price": 0.00754561123298,
		"volume_24h": 9960.06747787977,
		"percent_change_1h": 0.16748,
		"percent_change_24h": 5.60569,
		"percent_change_7d": -8.47937,
		"market_cap": 7637267.064740394
	},
	"BTC": {
		"last_updated": "2019-01-15T15:15:22.000Z",
		"price": 3682.15316997,
		"volume_24h": 5749412243.31838,
		"percent_change_1h": -0.336866,
		"percent_change_24h": 1.45495,
		"percent_change_7d": -9.16597,
		"market_cap": 64375636193.561005
	}
}