{
	"BAY": {
		"last_updated": "2020-03-06T23:47:02.000Z",
		"price": 0.17276672946090002,
		"floor": 0.2,
		"pegvote": "deflate",
		"volume_24h": 0,
		"percent_change_1h": 0,
		"percent_change_24h": -0.024669,
		"percent_change_7d": 797.716,
		"market_cap": 174619492.20293617
	},
	"BTC": {
		"last_updated": "2020-03-06T23:46:40.000Z",
		"price": 9122.18902728,
		"floor": 20000,
		"pegvote": "",
		"volume_24h": 40939861024.1775,
		"percent_change_1h": 0.172273,
		"percent_change_24h": 0.40245,
		"percent_change_7d": 5.14726,
		"market_cap": 166541405935.33676
	}
}