{
	"BAY": {
		"last_updated": "2020-02-28T13:52:04.000Z",
		"price": 0.013257513088402501,
		"floor": 0.2,
		"pegvote": "deflate",
		"volume_24h": 137.506791680246,
		"percent_change_1h": 1.0936,
		"percent_change_24h": -10.0391,
		"percent_change_7d": 0,
		"market_cap": 13435067.771177623
	},
	"BTC": {
		"last_updated": "2020-02-28T13:52:33.000Z",
		"price": 8665.04123425,
		"floor": 20000,
		"pegvote": "",
		"volume_24h": 42971229401.9228,
		"percent_change_1h": 1.72056,
		"percent_change_24h": -1.91443,
		"percent_change_7d": -10.5575,
		"market_cap": 158068652679.80673
	}
}