{
	"BAY": {
		"last_updated": "2020-02-27T14:23:02.000Z",
		"price": 0.0158121867494781,
		"floor": 0.2,
		"pegvote": "deflate",
		"volume_24h": 5706.44290995152,
		"percent_change_1h": 20.5442,
		"percent_change_24h": 13.7608,
		"percent_change_7d": 0,
		"market_cap": 16004609.481126644
	},
	"BTC": {
		"last_updated": "2020-02-27T14:22:40.000Z",
		"price": 8833.62388239,
		"floor": 20000,
		"pegvote": "",
		"volume_24h": 51954090263.4851,
		"percent_change_1h": 0.187607,
		"percent_change_24h": -3.16808,
		"percent_change_7d": -7.89355,
		"market_cap": 161128055705.44492
	}
}