{
	"BAY": {
		"last_updated": "2019-04-22T23:49:01.000Z",
		"price": 0.00973112201001,
		"volume_24h": 22962.6828684279,
		"percent_change_1h": 0.23409,
		"percent_change_24h": 2.05828,
		"percent_change_7d": 1.64996,
		"market_cap": 9849325.036146706
	},
	"BTC": {
		"last_updated": "2019-04-22T23:48:32.000Z",
		"price": 5397.74177724,
		"volume_24h": 14598302136.6969,
		"percent_change_1h": -0.304674,
		"percent_change_24h": 1.70335,
		"percent_change_7d": 6.48529,
		"market_cap": 95325399050.85962
	}
}