{
	"BAY": {
		"last_updated": "2019-01-24T13:39:01.000Z",
		"price": 0.00736322534223,
		"volume_24h": 27937.1507696141,
		"percent_change_1h": -0.676988,
		"percent_change_24h": -1.5887,
		"percent_change_7d": 7.46197,
		"market_cap": 7452665.749685868
	},
	"BTC": {
		"last_updated": "2019-01-24T13:39:26.000Z",
		"price": 3598.31639864,
		"volume_24h": 5417575100.01362,
		"percent_change_1h": 0.0290751,
		"percent_change_24h": -0.333237,
		"percent_change_7d": -1.19781,
		"market_cap": 62966308954.431595
	}
}