{
	"BAY": {
		"last_updated": "2019-01-01T16:21:04.000Z",
		"price": 0.0078893995558,
		"volume_24h": 11333.2178647543,
		"percent_change_1h": -1.1307,
		"percent_change_24h": -3.28542,
		"percent_change_7d": -8.69359,
		"market_cap": 7985231.352065411
	},
	"BTC": {
		"last_updated": "2019-01-01T16:20:21.000Z",
		"price": 3725.77998108,
		"volume_24h": 4172042560.26607,
		"percent_change_1h": -0.398259,
		"percent_change_24h": -2.01059,
		"percent_change_7d": -2.08567,
		"market_cap": 65040426972.07617
	}
}