{
	"BAY": {
		"last_updated": "2019-08-25T07:41:02.000Z",
		"price": 0.00344545598859,
		"floor": 0.2,
		"pegvote": "deflate",
		"volume_24h": 699.224891801227,
		"percent_change_1h": 0.528123,
		"percent_change_24h": -1.40267,
		"percent_change_7d": -67.1467,
		"market_cap": 3487307.6192501886
	},
	"BTC": {
		"last_updated": "2019-08-25T07:41:33.000Z",
		"price": 10133.2099834,
		"floor": 20000,
		"pegvote": "",
		"volume_24h": 14857696089.6995,
		"percent_change_1h": 0.443626,
		"percent_change_24h": -1.41914,
		"percent_change_7d": -0.917281,
		"market_cap": 181341514158.95035
	}
}