{
	"BAY": {
		"last_updated": "2019-01-05T00:11:05.000Z",
		"price": 0.00818241675017,
		"volume_24h": 10083.128648817,
		"percent_change_1h": 1.1712,
		"percent_change_24h": -0.713045,
		"percent_change_7d": -6.65201,
		"market_cap": 8281807.798806206
	},
	"BTC": {
		"last_updated": "2019-01-05T00:10:23.000Z",
		"price": 3854.38301967,
		"volume_24h": 4815291966.26878,
		"percent_change_1h": -0.105406,
		"percent_change_24h": 0.61045,
		"percent_change_7d": -2.08673,
		"market_cap": 67310100520.848366
	}
}