{
	"BAY": {
		"last_updated": "2019-07-31T21:16:01.000Z",
		"price": 0.00440778167486,
		"volume_24h": 2645.47134638457,
		"percent_change_1h": -1.55065,
		"percent_change_24h": 0.0162679,
		"percent_change_7d": -0.320071,
		"market_cap": 4461322.585351352
	},
	"BTC": {
		"last_updated": "2019-07-31T21:15:33.000Z",
		"price": 10022.8042597,
		"volume_24h": 16298681819.7855,
		"percent_change_1h": -0.0615782,
		"percent_change_24h": 4.41209,
		"percent_change_7d": 2.08862,
		"market_cap": 178903798624.2606
	}
}