{
	"BAY": {
		"last_updated": "2020-03-26T23:18:02.000Z",
		"price": 0.0666064568798929,
		"floor": 0.2,
		"floorjump": false,
		"pegvote": "deflate",
		"volume_24h": 12168.2324745603,
		"percent_change_1h": 0.426707,
		"percent_change_24h": 0.310314,
		"percent_change_7d": 69.1602,
		"market_cap": 67332258.07628734
	},
	"BTC": {
		"last_updated": "2020-03-26T23:17:36.000Z",
		"price": 6721.13591119,
		"floor": 20000,
		"floorjump": false,
		"pegvote": "",
		"volume_24h": 34913907416.8967,
		"percent_change_1h": 0.403625,
		"percent_change_24h": 0.796982,
		"percent_change_7d": 9.65832,
		"market_cap": 122920078850.62259
	}
}