{
	"BAY": {
		"last_updated": "2019-10-10T07:50:02.000Z",
		"price": 0.00318860940585,
		"floor": 0.2,
		"pegvote": "deflate",
		"volume_24h": 398.759391503878,
		"percent_change_1h": 0.45571,
		"percent_change_24h": -7.91264,
		"percent_change_7d": 9.57135,
		"market_cap": 3227341.145165541
	},
	"BTC": {
		"last_updated": "2019-10-10T07:50:34.000Z",
		"price": 8621.61919,
		"floor": 20000,
		"pegvote": "",
		"volume_24h": 20526663415.046,
		"percent_change_1h": 0.376019,
		"percent_change_24h": 4.61206,
		"percent_change_7d": 3.60458,
		"market_cap": 155050009729.51178
	}
}