{
	"BAY": {
		"last_updated": "2019-12-10T17:01:01.000Z",
		"price": 0.0147119120237,
		"floor": 0.2,
		"pegvote": "deflate",
		"volume_24h": 0,
		"percent_change_1h": 0,
		"percent_change_24h": -1.88554,
		"percent_change_7d": 902.209,
		"market_cap": 14890616.23886342
	},
	"BTC": {
		"last_updated": "2019-12-10T17:01:35.000Z",
		"price": 7282.75636346,
		"floor": 20000,
		"pegvote": "",
		"volume_24h": 18168029787.1586,
		"percent_change_1h": -0.107239,
		"percent_change_24h": -2.87373,
		"percent_change_7d": -0.887624,
		"market_cap": 131775103984.99068
	}
}