{
	"BAY": {
		"last_updated": "2020-02-28T16:13:02.000Z",
		"price": 0.005229210232572,
		"floor": 0.2,
		"pegvote": "deflate",
		"volume_24h": 427.227862546947,
		"percent_change_1h": 0.642311,
		"percent_change_24h": -67.0289,
		"percent_change_7d": 0,
		"market_cap": 5307842.3577203825
	},
	"BTC": {
		"last_updated": "2020-02-28T16:13:38.000Z",
		"price": 8715.35038762,
		"floor": 20000,
		"pegvote": "",
		"volume_24h": 43371320855.1109,
		"percent_change_1h": 0.621804,
		"percent_change_24h": -1.90069,
		"percent_change_7d": -10.0577,
		"market_cap": 158988576727.80435
	}
}