{
	"BAY": {
		"last_updated": "2020-04-08T18:38:05.000Z",
		"price": 0.1748228495433916,
		"floor": 0.2,
		"floorjump": false,
		"pegvote": "deflate",
		"volume_24h": 44250.9255786947,
		"percent_change_1h": 0.153662,
		"percent_change_24h": -16.0095,
		"percent_change_7d": 63.0603,
		"market_cap": 177214373.28709885
	},
	"BTC": {
		"last_updated": "2020-04-08T18:37:48.000Z",
		"price": 7296.44614121,
		"floor": 20000,
		"floorjump": false,
		"pegvote": "",
		"volume_24h": 38676180658.3236,
		"percent_change_1h": 0.00656958,
		"percent_change_24h": -0.364501,
		"percent_change_7d": 15.6218,
		"market_cap": 133617446838.98283
	}
}