{
	"BAY": {
		"last_updated": "2019-08-01T17:23:02.000Z",
		"price": 0.00455269740604,
		"volume_24h": 2842.58050275576,
		"percent_change_1h": 1.57329,
		"percent_change_24h": 2.93526,
		"percent_change_7d": -0.0375649,
		"market_cap": 4607998.59432282
	},
	"BTC": {
		"last_updated": "2019-08-01T17:23:31.000Z",
		"price": 10036.3342884,
		"volume_24h": 15218715007.4843,
		"percent_change_1h": 0.0414552,
		"percent_change_24h": 0.0937311,
		"percent_change_7d": 0.365947,
		"market_cap": 179162487443.598
	}
}