{
	"BAY": {
		"last_updated": "2019-06-04T23:47:01.000Z",
		"price": 0.00819682491848,
		"volume_24h": 65195.6052195739,
		"percent_change_1h": -0.856253,
		"percent_change_24h": -11.9069,
		"percent_change_7d": -13.792,
		"market_cap": 8296390.981784975
	},
	"BTC": {
		"last_updated": "2019-06-04T23:47:30.000Z",
		"price": 7684.63948132,
		"volume_24h": 24557028124.944,
		"percent_change_1h": 0.227113,
		"percent_change_24h": -6.77262,
		"percent_change_7d": -11.4909,
		"market_cap": 136332128557.8497
	}
}