{
	"BAY": {
		"last_updated": "2019-05-14T03:15:00.000Z",
		"price": 0.00862930988085,
		"volume_24h": 13301.4295690562,
		"percent_change_1h": -0.703827,
		"percent_change_24h": 4.34941,
		"percent_change_7d": -0.377992,
		"market_cap": 8734129.298419587
	},
	"BTC": {
		"last_updated": "2019-05-14T03:15:27.000Z",
		"price": 7882.49355379,
		"volume_24h": 29297251382.3159,
		"percent_change_1h": -0.511873,
		"percent_change_24h": 12.3085,
		"percent_change_7d": 34.3693,
		"market_cap": 139514026969.57883
	}
}