{
	"BAY": {
		"last_updated": "2019-06-06T05:22:01.000Z",
		"price": 0.00836828342068,
		"volume_24h": 17264.4671848225,
		"percent_change_1h": 1.33668,
		"percent_change_24h": 3.23894,
		"percent_change_7d": -9.33473,
		"market_cap": 8469932.17432593
	},
	"BTC": {
		"last_updated": "2019-06-06T05:21:32.000Z",
		"price": 7857.02175346,
		"volume_24h": 20707511101.6036,
		"percent_change_1h": -0.367223,
		"percent_change_24h": 0.443809,
		"percent_change_7d": -9.63019,
		"market_cap": 139408606234.70868
	}
}