{
	"BAY": {
		"last_updated": "2019-03-15T11:57:02.000Z",
		"price": 0.00686534559746,
		"volume_24h": 12798.6117198736,
		"percent_change_1h": 0.957526,
		"percent_change_24h": 1.61799,
		"percent_change_7d": 6.55963,
		"market_cap": 6948738.3063644115
	},
	"BTC": {
		"last_updated": "2019-03-15T11:57:27.000Z",
		"price": 3953.37557751,
		"volume_24h": 10954601652.4547,
		"percent_change_1h": 0.564667,
		"percent_change_24h": 0.97768,
		"percent_change_7d": 0.647269,
		"market_cap": 69538690395.72765
	}
}