{
	"BAY": {
		"last_updated": "2019-09-08T12:12:02.000Z",
		"price": 0.00208987559415,
		"floor": 0.2,
		"pegvote": "deflate",
		"volume_24h": 449.323252741298,
		"percent_change_1h": -15.1987,
		"percent_change_24h": 17.455,
		"percent_change_7d": 36.0023,
		"market_cap": 2115261.11693182
	},
	"BTC": {
		"last_updated": "2019-09-08T12:11:31.000Z",
		"price": 10448.3806849,
		"floor": 20000,
		"pegvote": "",
		"volume_24h": 15118486414.6582,
		"percent_change_1h": -0.494777,
		"percent_change_24h": 0.319446,
		"percent_change_7d": 8.66739,
		"market_cap": 187265668767.47955
	}
}