{
	"BAY": {
		"last_updated": "2019-09-23T11:51:01.000Z",
		"price": 0.00278903104431,
		"floor": 0.2,
		"pegvote": "deflate",
		"volume_24h": 139.451552215601,
		"percent_change_1h": -0.071368,
		"percent_change_24h": 3.01671,
		"percent_change_7d": 11.6108,
		"market_cap": 2822909.142754099
	},
	"BTC": {
		"last_updated": "2019-09-23T11:51:35.000Z",
		"price": 9961.67091332,
		"floor": 20000,
		"pegvote": "",
		"volume_24h": 12700916138.3073,
		"percent_change_1h": -0.0303713,
		"percent_change_24h": -0.758553,
		"percent_change_7d": -3.21393,
		"market_cap": 178838391322.0143
	}
}