{
	"BAY": {
		"last_updated": "2019-05-03T12:40:01.000Z",
		"price": 0.00860937493668,
		"volume_24h": 10586.16230223,
		"percent_change_1h": 2.49241,
		"percent_change_24h": -2.56035,
		"percent_change_7d": -9.04045,
		"market_cap": 8713952.206352938
	},
	"BTC": {
		"last_updated": "2019-05-03T12:39:28.000Z",
		"price": 5816.31274516,
		"volume_24h": 18560540210.6749,
		"percent_change_1h": 0.454559,
		"percent_change_24h": 6.48511,
		"percent_change_7d": 10.2348,
		"market_cap": 102833718004.79646
	}
}