{
	"BAY": {
		"last_updated": "2019-09-17T05:13:01.000Z",
		"price": 0.00297752952857,
		"floor": 0.2,
		"pegvote": "deflate",
		"volume_24h": 92.4060888175652,
		"percent_change_1h": -0.0227152,
		"percent_change_24h": 14.6346,
		"percent_change_7d": 51.8355,
		"market_cap": 3013697.300418542
	},
	"BTC": {
		"last_updated": "2019-09-17T05:13:32.000Z",
		"price": 10266.7158694,
		"floor": 20000,
		"pegvote": "",
		"volume_24h": 14840511323.3792,
		"percent_change_1h": -0.0636979,
		"percent_change_24h": -0.863759,
		"percent_change_7d": -0.492919,
		"market_cap": 184190016054.9707
	}
}