{
	"BAY": {
		"last_updated": "2019-07-08T17:45:01.000Z",
		"price": 0.00720170627843,
		"volume_24h": 2670.89018718207,
		"percent_change_1h": 0.270982,
		"percent_change_24h": 7.28453,
		"percent_change_7d": 20.7242,
		"market_cap": 7289184.728970695
	},
	"BTC": {
		"last_updated": "2019-07-08T17:45:27.000Z",
		"price": 11896.6781716,
		"volume_24h": 21901237747.6578,
		"percent_change_1h": 0.318393,
		"percent_change_24h": 4.87179,
		"percent_change_7d": 13.642,
		"market_cap": 211839092113.45828
	}
}