{
	"BAY": {
		"last_updated": "2019-01-17T22:37:04.000Z",
		"price": 0.00695996513201,
		"volume_24h": 17588.9786137214,
		"percent_change_1h": -0.345263,
		"percent_change_24h": 1.79772,
		"percent_change_7d": -8.92395,
		"market_cap": 7044507.175523921
	},
	"BTC": {
		"last_updated": "2019-01-17T22:37:26.000Z",
		"price": 3666.71938122,
		"volume_24h": 5410303271.24611,
		"percent_change_1h": -0.122805,
		"percent_change_24h": 0.457476,
		"percent_change_7d": -0.24502,
		"market_cap": 64119599148.08859
	}
}