{
	"BAY": {
		"last_updated": "2019-08-06T18:09:01.000Z",
		"price": 0.00245142498023,
		"volume_24h": 18749.828255613,
		"percent_change_1h": -7.19715,
		"percent_change_24h": -10.7643,
		"percent_change_7d": -44.4185,
		"market_cap": 2481202.2094860123
	},
	"BTC": {
		"last_updated": "2019-08-06T18:09:29.000Z",
		"price": 11719.2073561,
		"volume_24h": 22816683705.5009,
		"percent_change_1h": -0.6045,
		"percent_change_24h": -0.915636,
		"percent_change_7d": 21.8592,
		"market_cap": 209322762821.4684
	}
}