{
	"BAY": {
		"last_updated": "2019-04-01T21:56:01.000Z",
		"price": 0.00929235462019,
		"volume_24h": 147131.973683269,
		"percent_change_1h": 3.77068,
		"percent_change_24h": 14.1913,
		"percent_change_7d": 29.5279,
		"market_cap": 9405227.980005238
	},
	"BTC": {
		"last_updated": "2019-04-01T21:56:26.000Z",
		"price": 4155.56694819,
		"volume_24h": 10154545591.4975,
		"percent_change_1h": 0.121325,
		"percent_change_24h": 1.23762,
		"percent_change_7d": 4.66334,
		"market_cap": 73223271299.7556
	}
}