{
	"BAY": {
		"last_updated": "2019-04-13T23:47:01.000Z",
		"price": 0.00949082975995,
		"volume_24h": 2767.27174313046,
		"percent_change_1h": 0.28822,
		"percent_change_24h": 0.49571,
		"percent_change_7d": -14.9674,
		"market_cap": 9606113.978668088
	},
	"BTC": {
		"last_updated": "2019-04-13T23:47:29.000Z",
		"price": 5097.72982413,
		"volume_24h": 10818040062.1904,
		"percent_change_1h": 0.213611,
		"percent_change_24h": 0.247693,
		"percent_change_7d": -0.230956,
		"market_cap": 89945619449.40576
	}
}