{
	"BAY": {
		"last_updated": "2019-07-27T09:53:02.000Z",
		"price": 0.00473975575455,
		"volume_24h": 8769.91055511629,
		"percent_change_1h": 2.0606,
		"percent_change_24h": 3.88286,
		"percent_change_7d": -5.49668,
		"market_cap": 4797329.123043413
	},
	"BTC": {
		"last_updated": "2019-07-27T09:53:31.000Z",
		"price": 10085.9197953,
		"volume_24h": 14960522842.3233,
		"percent_change_1h": -0.156153,
		"percent_change_24h": 2.80069,
		"percent_change_7d": -4.7086,
		"market_cap": 179940494619.036
	}
}