{
	"BAY": {
		"last_updated": "2019-07-29T17:55:01.000Z",
		"price": 0.00448382053101,
		"volume_24h": 3952.84110936724,
		"percent_change_1h": -2.39553,
		"percent_change_24h": -2.08883,
		"percent_change_7d": -9.5493,
		"market_cap": 4538285.07835347
	},
	"BTC": {
		"last_updated": "2019-07-29T17:54:33.000Z",
		"price": 9514.326847,
		"volume_24h": 15738400936.6006,
		"percent_change_1h": -0.623466,
		"percent_change_24h": -0.418426,
		"percent_change_7d": -8.22242,
		"market_cap": 169789109038.9944
	}
}