{
	"BAY": {
		"last_updated": "2019-03-27T09:25:01.000Z",
		"price": 0.00732117780877,
		"volume_24h": 18919.4348363349,
		"percent_change_1h": 2.28671,
		"percent_change_24h": 3.01387,
		"percent_change_7d": -1.62341,
		"market_cap": 7410107.468781591
	},
	"BTC": {
		"last_updated": "2019-03-27T09:25:28.000Z",
		"price": 4050.36738677,
		"volume_24h": 11235934676.0259,
		"percent_change_1h": -0.0208926,
		"percent_change_24h": 2.30853,
		"percent_change_7d": 0.123159,
		"market_cap": 71337144203.89526
	}
}