{
	"BAY": {
		"last_updated": "2019-08-26T12:32:01.000Z",
		"price": 0.00352427326802,
		"floor": 0.2,
		"pegvote": "deflate",
		"volume_24h": 715.220163214839,
		"percent_change_1h": 0.161386,
		"percent_change_24h": 1.67341,
		"percent_change_7d": 27.9008,
		"market_cap": 3567082.284779233
	},
	"BTC": {
		"last_updated": "2019-08-26T12:32:34.000Z",
		"price": 10370.4897972,
		"floor": 20000,
		"pegvote": "",
		"volume_24h": 18711968705.2862,
		"percent_change_1h": 0.182859,
		"percent_change_24h": 1.6579,
		"percent_change_7d": -2.98121,
		"market_cap": 185610248603.5508
	}
}