{
	"BAY": {
		"last_updated": "2019-12-01T02:47:01.000Z",
		"price": 0.00454898976396,
		"floor": 0.2,
		"pegvote": "deflate",
		"volume_24h": 1284.94396607342,
		"percent_change_1h": 0.131807,
		"percent_change_24h": -4.58739,
		"percent_change_7d": -2.92928,
		"market_cap": 4604245.915862304
	},
	"BTC": {
		"last_updated": "2019-12-01T02:47:36.000Z",
		"price": 7456.77554219,
		"floor": 20000,
		"pegvote": "",
		"volume_24h": 18018080214.3531,
		"percent_change_1h": -0.0339291,
		"percent_change_24h": -4.57076,
		"percent_change_7d": 1.71317,
		"market_cap": 134790166055.73488
	}
}