{
	"BAY": {
		"last_updated": "2019-11-24T23:52:02.000Z",
		"price": 0.00430030495312,
		"floor": 0.2,
		"pegvote": "deflate",
		"volume_24h": 934.345163351879,
		"percent_change_1h": -0.900514,
		"percent_change_24h": -8.80587,
		"percent_change_7d": -7.45376,
		"market_cap": 4352540.353955234
	},
	"BTC": {
		"last_updated": "2019-11-24T23:51:37.000Z",
		"price": 7065.2102522,
		"floor": 20000,
		"pegvote": "",
		"volume_24h": 29957265250.945,
		"percent_change_1h": -0.780684,
		"percent_change_24h": -4.19992,
		"percent_change_7d": -17.9028,
		"market_cap": 127639290047.4867
	}
}