{
	"BAY": {
		"last_updated": "2019-07-10T10:00:03.000Z",
		"price": 0.00634419837455,
		"volume_24h": 6661.4785628235,
		"percent_change_1h": 0.148564,
		"percent_change_24h": -0.0418049,
		"percent_change_7d": -8.78605,
		"market_cap": 6421260.757028813
	},
	"BTC": {
		"last_updated": "2019-07-10T09:59:30.000Z",
		"price": 12955.8852532,
		"volume_24h": 28782840223.7103,
		"percent_change_1h": 0.164377,
		"percent_change_24h": 3.85904,
		"percent_change_7d": 14.3138,
		"market_cap": 230739613373.14508
	}
}